passgr/__init__.py
passgr/pass_generator.py
passgr-0.0.1.dist-info/METADATA
passgr-0.0.1.dist-info/WHEEL
passgr-0.0.1.dist-info/top_level.txt
passgr-0.0.1.dist-info/RECORD
