Metadata-Version: 2.1
Name: passgr
Version: 0.0.1
Summary: A simple password generator
Home-page: https://github.com/Davi-dev-C/simple-package-template
Author: davi h.
Author-email: davi.henrique.lima01@gmail.com
License: UNKNOWN
Platform: UNKNOWN
Requires-Python: >=3.8
